pytento/__init__.py
pytento/case.py
pytento/core.py
pytento-1.0.9.dist-info/DESCRIPTION.rst
pytento-1.0.9.dist-info/METADATA
pytento-1.0.9.dist-info/RECORD
pytento-1.0.9.dist-info/WHEEL
pytento-1.0.9.dist-info/metadata.json
pytento-1.0.9.dist-info/top_level.txt
