Metadata-Version: 2.0
Name: pytento
Version: 1.0.9
Summary: This is a staticly-typed testing framework
Home-page: https://github.com/demirantay/pytento
Author: Demir Antay
Author-email: demir99antay@gmail.com
License: MIT
Platform: UNKNOWN
